{"cameraMode":{"drawMode":0,"name":"Shaded","section":"Shading Mode"},"sceneLighting":true,"audioPlay":false,"sceneViewState":{"showFog":true,"showMaterialUpdate":false,"showSkybox":true,"showFlares":true,"showImageEffects":true,"showParticleSystems":true,"showVisualEffectGraphs":true,"m_FxEnabled":false},"in2DMode":false,"pivot":{"x":-29.350765228271486,"y":-25.216856002807618,"z":7.041552543640137},"rotation":{"x":0.26572367548942568,"y":-0.5891973972320557,"z":0.21373958885669709,"w":0.7324981689453125},"size":24.211994171142579,"orthographic":false}